hamlet/__about__.py
hamlet/__init__.py
hamlet/__main__.py
hamlet/__version__.py
hamlet/env.py
hamlet/loggers.py
hamlet/backend/__init__.py
hamlet/backend/automation/__init__.py
hamlet/backend/automation/confirm_builds/__init__.py
hamlet/backend/automation/construct_tree/__init__.py
hamlet/backend/automation/manage_build_references/__init__.py
hamlet/backend/automation/manage_images/__init__.py
hamlet/backend/automation/properties_file/__init__.py
hamlet/backend/automation/set_automation_context/__init__.py
hamlet/backend/automation/update_build_references/__init__.py
hamlet/backend/automation_tasks/__init__.py
hamlet/backend/automation_tasks/base.py
hamlet/backend/automation_tasks/transfer_image/__init__.py
hamlet/backend/automation_tasks/update_build/__init__.py
hamlet/backend/automation_tasks/upload_image/__init__.py
hamlet/backend/common/__init__.py
hamlet/backend/common/context.py
hamlet/backend/common/exceptions.py
hamlet/backend/common/fsutils.py
hamlet/backend/common/runner.py
hamlet/backend/common/shell_vars_to_json.py
hamlet/backend/common/shell_vars_to_json.sh
hamlet/backend/container_registry/__init__.py
hamlet/backend/create/__init__.py
hamlet/backend/create/template/__init__.py
hamlet/backend/create/template/context_tree.py
hamlet/backend/create/template/create_template.py
hamlet/backend/create/template/environment.py
hamlet/backend/create/template/set_context.py
hamlet/backend/create/template/utils.py
hamlet/backend/deploy/__init__.py
hamlet/backend/draw/__init__.py
hamlet/backend/draw/diagram.py
hamlet/backend/draw/diagram_schema.py
hamlet/backend/draw/render.py
hamlet/backend/engine/__init__.py
hamlet/backend/engine/common.py
hamlet/backend/engine/engine.py
hamlet/backend/engine/engine_code_source.py
hamlet/backend/engine/engine_loader.py
hamlet/backend/engine/engine_part.py
hamlet/backend/engine/engine_source.py
hamlet/backend/engine/exceptions.py
hamlet/backend/generate/__init__.py
hamlet/backend/generate/utils.py
hamlet_cli-9.2.0.dist-info/LICENSE
hamlet_cli-9.2.0.dist-info/METADATA
hamlet_cli-9.2.0.dist-info/WHEEL
hamlet_cli-9.2.0.dist-info/entry_points.txt
hamlet_cli-9.2.0.dist-info/top_level.txt
hamlet_cli-9.2.0.dist-info/RECORD
