Metadata-Version: 2.1
Name: hamlet-cli
Version: 9.2.0
Summary: UNKNOWN
Home-page: https://hamlet.io
Author: Hamlet
License: GPLv3
Project-URL: Repository, https://github.com/hamletio/executor-python
Platform: UNKNOWN
Classifier: Natural Language :: English
Classifier: Intended Audience :: Developers
Classifier: Intended Audience :: System Administrators
Classifier: License :: OSI Approved :: GNU General Public License v3 (GPLv3)
Classifier: Programming Language :: Java
Classifier: Programming Language :: Python
Requires-Python: >=3.6
License-File: LICENSE
Requires-Dist: click (<8.0.0,>=7.0.0)
Requires-Dist: click-configfile (<1.0.0,>=0.2.3)
Requires-Dist: pytest (<7.0.0,>=6.0.0)
Requires-Dist: cookiecutter (<2.0.0,>=1.7.0)
Requires-Dist: tabulate (<1.0.0,>=0.8.0)
Requires-Dist: Jinja2 (<3.0.0,>=2.11.0)
Requires-Dist: cfn-lint (<1.0.0,>=0.51.0)
Requires-Dist: cfn-flip (<2.0.0,>=1.2.0)
Requires-Dist: diagrams (<1.0.0,>=0.18.0)
Requires-Dist: marshmallow (<4.0.0,>=3.7.0)
Requires-Dist: jmespath (>=0.10.0<1.0.0)
Requires-Dist: importlib-resources (>=5.2.0<6.0.0)
Requires-Dist: www-authenticate (>=0.9.2<1.0.0)
Requires-Dist: httpx (>=0.18.2<1.0.0)
